aiassess/__init__.py
aiassess/_version.py
aiassess/async_client.py
aiassess/cli.py
aiassess/client.py
aiassess/exceptions.py
aiassess/py.typed
aiassess/types.py
aiassess-0.7.0.dist-info/LICENSE
aiassess-0.7.0.dist-info/METADATA
aiassess-0.7.0.dist-info/WHEEL
aiassess-0.7.0.dist-info/entry_points.txt
aiassess-0.7.0.dist-info/top_level.txt
aiassess-0.7.0.dist-info/RECORD
