Metadata-Version: 2.1
Name: aiassess
Version: 0.7.0
Summary: Python SDK for AI Assess Tech - Ethical AI Assessment Platform
Author-email: Greg Spehar <greg@gidanc.ai>, AI Assess Tech <sdk@aiassess.tech>
Maintainer-email: AI Assess Tech <sdk@aiassess.tech>
Project-URL: Homepage, https://www.aiassesstech.com
Project-URL: Documentation, https://www.aiassesstech.com/docs/sdk/python
Project-URL: Repository, https://github.com/aiassesstech/aiassess-python
Project-URL: Changelog, https://github.com/aiassesstech/aiassess-python/blob/main/CHANGELOG.md
Project-URL: Bug Tracker, https://github.com/aiassesstech/aiassess-python/issues
Keywords: ai,assessment,safety,ethics,testing,ethical-ai,responsible-ai,ai-safety,llm,4d-framework,compliance,certification
Classifier: Development Status :: 4 - Beta
Classifier: Intended Audience :: Developers
Classifier: Intended Audience :: Science/Research
Classifier: Operating System :: OS Independent
Classifier: Programming Language :: Python :: 3
Classifier: Programming Language :: Python :: 3.8
Classifier: Programming Language :: Python :: 3.9
Classifier: Programming Language :: Python :: 3.10
Classifier: Programming Language :: Python :: 3.11
Classifier: Programming Language :: Python :: 3.12
Classifier: Programming Language :: Python :: 3.13
Classifier: Topic :: Scientific/Engineering :: Artificial Intelligence
Classifier: Topic :: Software Development :: Quality Assurance
Classifier: Topic :: Software Development :: Testing
Classifier: Typing :: Typed
Requires-Python: >=3.8
License-File: LICENSE
Requires-Dist: httpx>=0.25.0
Requires-Dist: pydantic>=2.0.0
Provides-Extra: dev
Requires-Dist: pytest>=7.0.0; extra == "dev"
Requires-Dist: pytest-asyncio>=0.21.0; extra == "dev"
Requires-Dist: pytest-cov>=4.0.0; extra == "dev"
Requires-Dist: pytest-httpx>=0.21.0; extra == "dev"
Requires-Dist: black>=23.0.0; extra == "dev"
Requires-Dist: ruff>=0.1.0; extra == "dev"
Requires-Dist: mypy>=1.0.0; extra == "dev"
Requires-Dist: pre-commit>=3.0.0; extra == "dev"
Provides-Extra: docs
Requires-Dist: mkdocs>=1.5.0; extra == "docs"
Requires-Dist: mkdocs-material>=9.0.0; extra == "docs"
Requires-Dist: mkdocstrings[python]>=0.24.0; extra == "docs"
